[{
"firstName":"Casey",
"lastName":"Siffa",
"userName":"Csiffa",
"password": "iLoveLoMein77",
"email":"csiffa@sb.gov",
"phoneNumber": 8439910012,
"clearanceLevel": 2,
"ID":2149921,
"policeDepartment":"Santa Barbra Police Station",
"myCriminals": [],
"myCases": []
},{
"firstName":"Jonathan",
"lastName":"Baker",
"userName":"Jbaker",
"password": "i444!@@@calI",
"email":"Jbaker@sb.gov",
"phoneNumber": 8649010012,
"clearanceLevel": 1,
"ID":119521,
"policeDepartment":"Santa Barbra Police Station",
"myCriminals": [],
"myCases": []
},{
"firstName":"Clark",
"lastName":"Smith",
"userName":"Csmith",
"password": "LiveLuvLaugh1999",
"email":"Csmith@sb.gov",
"phoneNumber": 8439243002,
"clearanceLevel": 2,
"ID":4449921,
"policeDepartment":"Santa Barbra Police Station",
"myCriminals": [],
"myCases": []
},{
"firstName":"Ben",
"lastName":"Fields",
"userName":"Bfields",
"password": "iLovePoodles44",
"email":"bfields@sb.gov",
"phoneNumber": 8432210012,
"clearanceLevel": 1,
"ID":3345221,
"policeDepartment":"Santa Barbra Police Station",
"myCriminals": [],
"myCases": []
},{
"firstName":"Alex",
"lastName":"Marant",
"userName":"Amarant",
"password": "LakeMurz21!",
"email":"Amarant@sb.gov",
"phoneNumber": 8642219012,
"clearanceLevel": 1,
"ID":3349221,
"policeDepartment":"Santa Barbra Police Station",
"myCriminals": [],
"myCases": []
},{
"firstName":"Emily",
"lastName":"Barron",
"userName":"Ebarron",
"password": "MulanIs98@91",
"email":"Ebarron@sb.gov",
"phoneNumber": 8432328812,
"clearanceLevel": 1,
"ID":3374221,
"policeDepartment":"Santa Barbra Police Station",
"myCriminals": [],
"myCases": []
}]
