[{
"description":"Victim was sexually assualted at a night Pawleys Night club at 22:34.",
"contact":"(864)-331-4455",
"victimID":1922
},{
"description":"Victim home Address 144 Place St, was set on fire at buring down the entire home 02:31.",
"contact":"(864)-991-4255",
"victimID":1972
},{
"description":"Victim was robbed of wallet on 144 Wailing St at 13:04",
"contact":"(864)-131-4955",
"victimID":1322
},{
"description":"Victim car was stolen at the 1444 Sumter HWY BP gas station at 19:00",
"contact":"(864)-345-4475",
"victimID":1942
},{
"description":"Victim was assualted at 5599 Business St, Family Law Firm LLC at 10:29",
"contact":"(824)-341-1955",
"victimID":1931
},{
"description":"Victim was assualted at 220 Calhoun Ave at 22:54",
"contact":"(891)-331-9005",
"victimID":19782
}]